dummy_localstack-0.16.8.data/scripts/localstack
dummy_localstack-0.16.8.data/scripts/localstack.bat
localstack/__init__.py
localstack/config.py
localstack/constants.py
localstack/package.json
localstack/plugins.py
localstack/aws/__init__.py
localstack/aws/app.py
localstack/aws/chain.py
localstack/aws/forwarder.py
localstack/aws/gateway.py
localstack/aws/proxy.py
localstack/aws/scaffold.py
localstack/aws/skeleton.py
localstack/aws/spec.py
localstack/aws/api/__init__.py
localstack/aws/api/core.py
localstack/aws/api/acm/__init__.py
localstack/aws/api/apigateway/__init__.py
localstack/aws/api/awslambda/__init__.py
localstack/aws/api/cloudformation/__init__.py
localstack/aws/api/cloudwatch/__init__.py
localstack/aws/api/config/__init__.py
localstack/aws/api/dynamodb/__init__.py
localstack/aws/api/dynamodbstreams/__init__.py
localstack/aws/api/ec2/__init__.py
localstack/aws/api/es/__init__.py
localstack/aws/api/events/__init__.py
localstack/aws/api/firehose/__init__.py
localstack/aws/api/iam/__init__.py
localstack/aws/api/kms/__init__.py
localstack/aws/api/logs/__init__.py
localstack/aws/api/opensearch/__init__.py
localstack/aws/api/redshift/__init__.py
localstack/aws/api/resource_groups/__init__.py
localstack/aws/api/resourcegroupstaggingapi/__init__.py
localstack/aws/api/route53/__init__.py
localstack/aws/api/route53resolver/__init__.py
localstack/aws/api/s3control/__init__.py
localstack/aws/api/secretsmanager/__init__.py
localstack/aws/api/ses/__init__.py
localstack/aws/api/sns/__init__.py
localstack/aws/api/sqs/__init__.py
localstack/aws/api/ssm/__init__.py
localstack/aws/api/stepfunctions/__init__.py
localstack/aws/api/sts/__init__.py
localstack/aws/api/support/__init__.py
localstack/aws/api/swf/__init__.py
localstack/aws/handlers/__init__.py
localstack/aws/handlers/auth.py
localstack/aws/handlers/codec.py
localstack/aws/handlers/cors.py
localstack/aws/handlers/fallback.py
localstack/aws/handlers/internal.py
localstack/aws/handlers/legacy.py
dummy_localstack-0.16.8.dist-info/LICENSE.txt
dummy_localstack-0.16.8.dist-info/METADATA
dummy_localstack-0.16.8.dist-info/WHEEL
dummy_localstack-0.16.8.dist-info/top_level.txt
dummy_localstack-0.16.8.dist-info/RECORD
