Metadata-Version: 2.1
Name: dummy-localstack
Version: 0.16.8
Summary: LocalStack - A fully functional local Cloud stack
Home-page: https://github.com/localstack/localstack
Author: LocalStack Contributors
Author-email: info@localstack.cloud
License: Apache License 2.0
Classifier: Programming Language :: Python :: 3.6
Classifier: Programming Language :: Python :: 3.7
Classifier: Programming Language :: Python :: 3.8
Classifier: Programming Language :: Python :: 3.9
Classifier: Programming Language :: Python :: 3.10
Classifier: License :: OSI Approved :: Apache Software License
Classifier: Topic :: Internet
Classifier: Topic :: Software Development :: Testing
Classifier: Topic :: System :: Emulators
License-File: LICENSE.txt
Requires-Dist: boto3 (>=1.20)
Requires-Dist: click (>=7.0)
Requires-Dist: cachetools (<4.0.0,>=3.1.1)
Requires-Dist: localstack-client (>=1.31)
Requires-Dist: dummy-localstack-ext (==0.16.8)
Requires-Dist: plux (>=1.3.1)
Requires-Dist: psutil (<6.0.0,>=5.4.8)
Requires-Dist: python-dotenv (>=0.19.1)
Requires-Dist: pyyaml (>=5.1)
Requires-Dist: rich (>=12.3.0)
Requires-Dist: requests (<2.26,>=2.20.0)
Requires-Dist: semver (>=2.10)
Requires-Dist: stevedore (>=3.4.0)
Requires-Dist: tailer (>=0.4.1)
Requires-Dist: apispec (>=5.1.1)
Requires-Dist: dataclasses ; python_version < "3.7"
Requires-Dist: typing-extensions ; python_version < "3.8"
Provides-Extra: dev
Requires-Dist: black (==22.3.0) ; extra == 'dev'
Requires-Dist: coveralls (==3.1.0) ; extra == 'dev'
Requires-Dist: Cython ; extra == 'dev'
Requires-Dist: flake8 (>=3.6.0) ; extra == 'dev'
Requires-Dist: flake8-black (==0.3.2) ; extra == 'dev'
Requires-Dist: flake8-isort (>=4.0.0) ; extra == 'dev'
Requires-Dist: flake8-quotes (>=0.11.0) ; extra == 'dev'
Requires-Dist: pre-commit (==2.13.0) ; extra == 'dev'
Requires-Dist: pyproject-flake8 ; extra == 'dev'
Requires-Dist: isort (==5.9.1) ; extra == 'dev'
Requires-Dist: pandoc ; extra == 'dev'
Requires-Dist: pypandoc ; extra == 'dev'
Requires-Dist: autoflake ; extra == 'dev'
Provides-Extra: full
Requires-Dist: airspeed (==0.5.19) ; extra == 'full'
Requires-Dist: amazon-kclpy-ext (==1.5.1) ; extra == 'full'
Requires-Dist: aws-sam-translator (>=1.15.1) ; extra == 'full'
Requires-Dist: awscli (>=1.22.90) ; extra == 'full'
Requires-Dist: boto (>=2.49.0) ; extra == 'full'
Requires-Dist: botocore (>=1.12.13) ; extra == 'full'
Requires-Dist: cbor2 (>=5.2.0) ; extra == 'full'
Requires-Dist: crontab (>=0.22.6) ; extra == 'full'
Requires-Dist: cryptography ; extra == 'full'
Requires-Dist: docker (==5.0.0) ; extra == 'full'
Requires-Dist: flask (>=1.0.2) ; extra == 'full'
Requires-Dist: flask-cors (<3.1.0,>=3.0.3) ; extra == 'full'
Requires-Dist: flask-swagger (==0.2.12) ; extra == 'full'
Requires-Dist: jsonpatch (<2.0,>=1.24) ; extra == 'full'
Requires-Dist: jsonpath-rw (<2.0.0,>=1.4.0) ; extra == 'full'
Requires-Dist: dummy-localstack-ext[runtime] (==0.16.8) ; extra == 'full'
Requires-Dist: moto-ext[all] (==3.1.10) ; extra == 'full'
Requires-Dist: opensearch-py (==1.1.0) ; extra == 'full'
Requires-Dist: pproxy (>=2.7.0) ; extra == 'full'
Requires-Dist: pyopenssl (>=21.0.0) ; extra == 'full'
Requires-Dist: Quart (>=0.6.15) ; extra == 'full'
Requires-Dist: readerwriterlock (>=1.0.7) ; extra == 'full'
Requires-Dist: requests-aws4auth (==0.9) ; extra == 'full'
Requires-Dist: Werkzeug (>=2.0) ; extra == 'full'
Requires-Dist: xmltodict (>=0.11.0) ; extra == 'full'
Provides-Extra: runtime
Requires-Dist: airspeed (==0.5.19) ; extra == 'runtime'
Requires-Dist: amazon-kclpy-ext (==1.5.1) ; extra == 'runtime'
Requires-Dist: aws-sam-translator (>=1.15.1) ; extra == 'runtime'
Requires-Dist: awscli (>=1.22.90) ; extra == 'runtime'
Requires-Dist: boto (>=2.49.0) ; extra == 'runtime'
Requires-Dist: botocore (>=1.12.13) ; extra == 'runtime'
Requires-Dist: cbor2 (>=5.2.0) ; extra == 'runtime'
Requires-Dist: crontab (>=0.22.6) ; extra == 'runtime'
Requires-Dist: cryptography ; extra == 'runtime'
Requires-Dist: docker (==5.0.0) ; extra == 'runtime'
Requires-Dist: flask (>=1.0.2) ; extra == 'runtime'
Requires-Dist: flask-cors (<3.1.0,>=3.0.3) ; extra == 'runtime'
Requires-Dist: flask-swagger (==0.2.12) ; extra == 'runtime'
Requires-Dist: jsonpatch (<2.0,>=1.24) ; extra == 'runtime'
Requires-Dist: jsonpath-rw (<2.0.0,>=1.4.0) ; extra == 'runtime'
Requires-Dist: dummy-localstack-ext[runtime] (==0.16.8) ; extra == 'runtime'
Requires-Dist: moto-ext[all] (==3.1.10) ; extra == 'runtime'
Requires-Dist: opensearch-py (==1.1.0) ; extra == 'runtime'
Requires-Dist: pproxy (>=2.7.0) ; extra == 'runtime'
Requires-Dist: pyopenssl (>=21.0.0) ; extra == 'runtime'
Requires-Dist: Quart (>=0.6.15) ; extra == 'runtime'
Requires-Dist: readerwriterlock (>=1.0.7) ; extra == 'runtime'
Requires-Dist: requests-aws4auth (==0.9) ; extra == 'runtime'
Requires-Dist: Werkzeug (>=2.0) ; extra == 'runtime'
Requires-Dist: xmltodict (>=0.11.0) ; extra == 'runtime'
Provides-Extra: test
Requires-Dist: pytest (==6.2.4) ; extra == 'test'
Requires-Dist: pytest-httpserver (>=1.0.1) ; extra == 'test'
Requires-Dist: pytest-rerunfailures (==10.0) ; extra == 'test'
Requires-Dist: coverage[toml] (>=5.5) ; extra == 'test'
Requires-Dist: jsonpath-ng (>=1.5.3) ; extra == 'test'
